gspread10/__init__.py
gsspread10-0.0.2.dist-info/LICENSE.txt
gsspread10-0.0.2.dist-info/METADATA
gsspread10-0.0.2.dist-info/WHEEL
gsspread10-0.0.2.dist-info/top_level.txt
gsspread10-0.0.2.dist-info/RECORD
