Metadata-Version: 2.1
Name: gsspread10
Version: 0.0.2
Summary: Package which helps us to read the data from google sheets 
Home-page: https://github.com/abhi10sharma/Google-Spread-Sheet
Author: Abhishek Sharma
Author-email: abhishekbangana1847@gmail.com
License: MIT
Platform: UNKNOWN
Classifier: Programming Language :: Python :: 3
Classifier: License :: OSI Approved :: MIT License
Classifier: Operating System :: Microsoft :: Windows :: Windows 10
Requires-Dist: gspread
Requires-Dist: oauth2client
Requires-Dist: pandas
Requires-Dist: matplotlib
